OAM_KIST/__init__.py
OAM_KIST/holography.py
OAM_KIST/utils.py
oam_kist-0.2.24.dist-info/METADATA
oam_kist-0.2.24.dist-info/WHEEL
oam_kist-0.2.24.dist-info/top_level.txt
oam_kist-0.2.24.dist-info/RECORD
