Metadata-Version: 2.4
Name: OAM_KIST
Version: 0.2.24
Summary: Quantum information and technology using OAM states and SLM for KIST research
Author: Youngjun Kim
Author-email: kyjun0915@kist.re.kr
Project-URL: Documentation, https://yjun0915.github.io/OAM_KIST/
Project-URL: Source, https://github.com/yjun0915/OAM_KIST
Requires-Python: >=3.7
Requires-Dist: numpy
Requires-Dist: matplotlib
Requires-Dist: scipy
Requires-Dist: opencv-python
Dynamic: author
Dynamic: author-email
Dynamic: description
Dynamic: description-content-type
Dynamic: project-url
Dynamic: requires-dist
Dynamic: requires-python
Dynamic: summary
